odoo8_addon_quick_purchase-8.0.1.0.0.99.dev4-py2.7-nspkg.pth
odoo8_addon_quick_purchase-8.0.1.0.0.99.dev4.dist-info/METADATA
odoo8_addon_quick_purchase-8.0.1.0.0.99.dev4.dist-info/RECORD
odoo8_addon_quick_purchase-8.0.1.0.0.99.dev4.dist-info/WHEEL
odoo8_addon_quick_purchase-8.0.1.0.0.99.dev4.dist-info/namespace_packages.txt
odoo8_addon_quick_purchase-8.0.1.0.0.99.dev4.dist-info/top_level.txt
odoo_addons/quick_purchase/README.rst
odoo_addons/quick_purchase/__init__.py
odoo_addons/quick_purchase/__openerp__.py
odoo_addons/quick_purchase/i18n/fr.po
odoo_addons/quick_purchase/i18n/quick_purchase.pot
odoo_addons/quick_purchase/models/__init__.py
odoo_addons/quick_purchase/models/product_product.py
odoo_addons/quick_purchase/models/purchase_order.py
odoo_addons/quick_purchase/static/description/01_purchase_order_create.png
odoo_addons/quick_purchase/static/description/02_purchase_order_add_product.png
odoo_addons/quick_purchase/static/description/03_purchase_order_updated.png
odoo_addons/quick_purchase/static/description/04_purchase_order_update_product_qty.png
odoo_addons/quick_purchase/static/description/icon.png
odoo_addons/quick_purchase/tests/__init__.py
odoo_addons/quick_purchase/tests/test_quick_purchase.py
odoo_addons/quick_purchase/views/product_view.xml
odoo_addons/quick_purchase/views/purchase_view.xml
